wfork_streamlit_profiler/__init__.py
wfork_streamlit_profiler/py.typed
wfork_streamlit_profiler-1.6.0.dist-info/LICENSE
wfork_streamlit_profiler-1.6.0.dist-info/METADATA
wfork_streamlit_profiler-1.6.0.dist-info/WHEEL
wfork_streamlit_profiler-1.6.0.dist-info/RECORD
