Metadata-Version: 2.3
Name: wfork-streamlit-profiler
Version: 1.6.0
Summary: (fork of) Runtime profiler for Streamlit, powered by pyinstrument
License: MIT
Author: Wyatt S Carpenter
Requires-Python: >=3.8
Classifier: License :: OSI Approved :: MIT License
Classifier: Programming Language :: Python :: 3
Classifier: Programming Language :: Python :: 3.8
Classifier: Programming Language :: Python :: 3.9
Classifier: Programming Language :: Python :: 3.10
Classifier: Programming Language :: Python :: 3.11
Classifier: Programming Language :: Python :: 3.12
Classifier: Programming Language :: Python :: 3.13
Provides-Extra: dev
Requires-Dist: black (>=21.12b0,<22.0) ; extra == "dev"
Requires-Dist: pyinstrument (>=5.0.2,<5.1.0)
Requires-Dist: streamlit (>=1.0,<2.0)
Requires-Dist: typegun ; extra == "dev"
Requires-Dist: types-openpyxl ; extra == "dev"
Requires-Dist: types-python-dateutil ; extra == "dev"
Requires-Dist: typing-extensions (>=4.5)
Project-URL: Homepage, https://github.com/wyattscarpenter/streamlit-profiler
